{
	"background": "assets/Background3.png",
	"stage": "assets/Stage3.png",
	"floor": "assets/Floor3.bmp",

	"enemies":[
		{
			"delay": 0.5,
			"list":[
				
				{
					"x": 0,
					"y": 0,
					"z": 1,
					"id": "tree3"
				},
				{
					"x": 200,
					"y": 0,
					"z": 1,
					"id": "tree3_2"
				},
				{
					"x": -200,
					"y": 0,
					"z": 1,
					"id": "tree3_3"
				}
			]
		},
		{
			"delay": 0.5,
			"list":[
				
				{
					"x": 0,
					"y": 0,
					"z": 1,
					"id": "tree3"
				},
				{
					"x": 200,
					"y": 0,
					"z": 1,
					"id": "tree3_2"
				},
				{
					"x": -200,
					"y": 0,
					"z": 1,
					"id": "tree3_3"
				}
			]
		},
		{
			"delay": 0.5,
			"list":[
				
				{
					"x": 0,
					"y": 0,
					"z": 1,
					"id": "tree3"
				},
				{
					"x": 200,
					"y": 0,
					"z": 1,
					"id": "tree3_2"
				},
				{
					"x": -200,
					"y": 0,
					"z": 1,
					"id": "tree3_3"
				}
			]
		},
		{
			"delay": 0.5,
			"list":[
				
				{
					"x": 0,
					"y": 0,
					"z": 1,
					"id": "tree3"
				},
				{
					"x": 200,
					"y": 0,
					"z": 1,
					"id": "tree3_2"
				},
				{
					"x": -200,
					"y": 0,
					"z": 1,
					"id": "tree3_3"
				}
			]
		},
		{
			"delay": 5,
			"list":[
				{
					"x": -250,
					"y": 100,
					"z": 0,
					"id": "drone0"
				}
			]
		},
		{
			"delay": 0,
			"list":[
				{
					"x": -250,
					"y": 100,
					"z": 0,
					"id": "drone0"
				}
			]
		}
	]
}
